pygna2/__init__.py
pygna2/matrix.py
pygna2/network.py
pygna2/parse_network_genesets.py
pygna2/pygna2.py
pygna2/test_association.py
pygna2/test_plot.py
pygna2/test_topology.py
pygna2/version.py
pygna2-0.3.14.dist-info/LICENSE
pygna2-0.3.14.dist-info/METADATA
pygna2-0.3.14.dist-info/WHEEL
pygna2-0.3.14.dist-info/entry_points.txt
pygna2-0.3.14.dist-info/top_level.txt
pygna2-0.3.14.dist-info/RECORD
