Metadata-Version: 2.1
Name: pygna2
Version: 0.3.14
Summary: Geneset Network Analysis
Author-email: Anthony Aylward <aaylward@salk.edu>
Project-URL: Homepage, https://gitlab.com/salk-tm/pygna2
Project-URL: Documentation, https://salk-tm.gitlab.io/pygna2
Classifier: Programming Language :: Python :: 3
Classifier: Operating System :: OS Independent
Classifier: License :: OSI Approved :: MIT License
Requires-Python: >=3.8
License-File: LICENSE
Requires-Dist: numpy <1.20
Requires-Dist: pygna
